simple_migrator/.vscode/settings.json
simple_migrator/__init__.py
simple_migrator/database/__init__.py
simple_migrator/database/config.py
simple_migrator/database/database_class.py
simple_migrator/database/database_type.py
simple_migrator/database/tables/__init__.py
simple_migrator/database/tables/base.py
simple_migrator/database/tables/constants.py
simple_migrator/database/tables/migrations_table.py
simple_migrator/migrator.py
simple_migrator/templates/config.txt
simple_migrator/utils/__init__.py
simple_migrator/utils/cli.py
simple_migrator/utils/constants.py
simple_migrator/utils/decorators.py
simple_migrator/utils/migration_tools.py
simple_migrator-0.1.9.dist-info/METADATA
simple_migrator-0.1.9.dist-info/WHEEL
simple_migrator-0.1.9.dist-info/entry_points.txt
simple_migrator-0.1.9.dist-info/RECORD
