Metadata-Version: 2.1
Name: simple_migrator
Version: 0.1.9
Summary: A simple migrator with no bs.
Home-page: https://h-tiwari-dev.github.io/Simple-Migrator
License: MIT
Author: Harsh Tiwari
Requires-Python: >=3.9,<4.0
Classifier: License :: OSI Approved :: MIT License
Classifier: Programming Language :: Python :: 3
Classifier: Programming Language :: Python :: 3.9
Classifier: Programming Language :: Python :: 3.10
Classifier: Programming Language :: Python :: 3.11
Classifier: Programming Language :: Python :: 3.12
Requires-Dist: build (==1.0.3)
Requires-Dist: click (==8.1.7)
Requires-Dist: colored (>=2.2.4,<3.0.0)
Requires-Dist: mysqlclient (==2.2.1)
Requires-Dist: packaging (==23.2)
Requires-Dist: pathlib (>=1.0.1,<2.0.0)
Requires-Dist: pip-tools (==7.3.0)
Requires-Dist: prettytable (>=3.9.0,<4.0.0)
Requires-Dist: psycopg2 (>=2.9.9,<3.0.0)
Requires-Dist: pyproject-hooks (==1.0.0)
Requires-Dist: python-dotenv (>=1.0.0,<2.0.0)
Requires-Dist: sqlalchemy (==2.0.23)
Requires-Dist: typing-extensions (==4.9.0)
Requires-Dist: wheel (==0.42.0)
